NaturalLanguageProcessingWithPytorchZhongwenban/README.md
NaturalLanguageProcessingWithPytorchZhongwenban/__init__.py
NaturalLanguageProcessingWithPytorchZhongwenban/__main__.py
NaturalLanguageProcessingWithPytorchZhongwenban/file.epub
NaturalLanguageProcessingWithPytorchZhongwenban/index.html
NaturalLanguageProcessingWithPytorchZhongwenban/css/__init__.py
NaturalLanguageProcessingWithPytorchZhongwenban/css/annotations.css
NaturalLanguageProcessingWithPytorchZhongwenban/css/main.css
NaturalLanguageProcessingWithPytorchZhongwenban/css/normalize.css
NaturalLanguageProcessingWithPytorchZhongwenban/css/popup.css
NaturalLanguageProcessingWithPytorchZhongwenban/font/__init__.py
NaturalLanguageProcessingWithPytorchZhongwenban/font/fontello.eot
NaturalLanguageProcessingWithPytorchZhongwenban/font/fontello.svg
NaturalLanguageProcessingWithPytorchZhongwenban/font/fontello.ttf
NaturalLanguageProcessingWithPytorchZhongwenban/font/fontello.woff
NaturalLanguageProcessingWithPytorchZhongwenban/img/__init__.py
NaturalLanguageProcessingWithPytorchZhongwenban/img/annotator-glyph-sprite.png
NaturalLanguageProcessingWithPytorchZhongwenban/img/annotator-icon-sprite.png
NaturalLanguageProcessingWithPytorchZhongwenban/img/apple-touch-icon.png
NaturalLanguageProcessingWithPytorchZhongwenban/img/cancelfullscreen.png
NaturalLanguageProcessingWithPytorchZhongwenban/img/close.png
NaturalLanguageProcessingWithPytorchZhongwenban/img/fullscreen.png
NaturalLanguageProcessingWithPytorchZhongwenban/img/loader.gif
NaturalLanguageProcessingWithPytorchZhongwenban/img/menu-icon.png
NaturalLanguageProcessingWithPytorchZhongwenban/img/save.png
NaturalLanguageProcessingWithPytorchZhongwenban/img/saved.png
NaturalLanguageProcessingWithPytorchZhongwenban/img/settings-s.png
NaturalLanguageProcessingWithPytorchZhongwenban/img/settings.png
NaturalLanguageProcessingWithPytorchZhongwenban/img/star.png
NaturalLanguageProcessingWithPytorchZhongwenban/js/__init__.py
natural_language_processing_with_pytorch_zhongwenban-2024.3.5.0.dist-info/METADATA
natural_language_processing_with_pytorch_zhongwenban-2024.3.5.0.dist-info/WHEEL
natural_language_processing_with_pytorch_zhongwenban-2024.3.5.0.dist-info/entry_points.txt
natural_language_processing_with_pytorch_zhongwenban-2024.3.5.0.dist-info/top_level.txt
natural_language_processing_with_pytorch_zhongwenban-2024.3.5.0.dist-info/RECORD
